XuechengDaxueJisuanjiYuWangluoanquanJiangyiCis643644V01/README.md
XuechengDaxueJisuanjiYuWangluoanquanJiangyiCis643644V01/__init__.py
XuechengDaxueJisuanjiYuWangluoanquanJiangyiCis643644V01/__main__.py
XuechengDaxueJisuanjiYuWangluoanquanJiangyiCis643644V01/file.epub
XuechengDaxueJisuanjiYuWangluoanquanJiangyiCis643644V01/index.html
XuechengDaxueJisuanjiYuWangluoanquanJiangyiCis643644V01/css/__init__.py
XuechengDaxueJisuanjiYuWangluoanquanJiangyiCis643644V01/css/annotations.css
XuechengDaxueJisuanjiYuWangluoanquanJiangyiCis643644V01/css/main.css
XuechengDaxueJisuanjiYuWangluoanquanJiangyiCis643644V01/css/normalize.css
XuechengDaxueJisuanjiYuWangluoanquanJiangyiCis643644V01/css/popup.css
XuechengDaxueJisuanjiYuWangluoanquanJiangyiCis643644V01/font/__init__.py
XuechengDaxueJisuanjiYuWangluoanquanJiangyiCis643644V01/font/fontello.eot
XuechengDaxueJisuanjiYuWangluoanquanJiangyiCis643644V01/font/fontello.svg
XuechengDaxueJisuanjiYuWangluoanquanJiangyiCis643644V01/font/fontello.ttf
XuechengDaxueJisuanjiYuWangluoanquanJiangyiCis643644V01/font/fontello.woff
XuechengDaxueJisuanjiYuWangluoanquanJiangyiCis643644V01/img/__init__.py
XuechengDaxueJisuanjiYuWangluoanquanJiangyiCis643644V01/img/annotator-glyph-sprite.png
XuechengDaxueJisuanjiYuWangluoanquanJiangyiCis643644V01/img/annotator-icon-sprite.png
XuechengDaxueJisuanjiYuWangluoanquanJiangyiCis643644V01/img/apple-touch-icon.png
XuechengDaxueJisuanjiYuWangluoanquanJiangyiCis643644V01/img/cancelfullscreen.png
XuechengDaxueJisuanjiYuWangluoanquanJiangyiCis643644V01/img/close.png
XuechengDaxueJisuanjiYuWangluoanquanJiangyiCis643644V01/img/fullscreen.png
XuechengDaxueJisuanjiYuWangluoanquanJiangyiCis643644V01/img/loader.gif
XuechengDaxueJisuanjiYuWangluoanquanJiangyiCis643644V01/img/menu-icon.png
XuechengDaxueJisuanjiYuWangluoanquanJiangyiCis643644V01/img/save.png
XuechengDaxueJisuanjiYuWangluoanquanJiangyiCis643644V01/img/saved.png
XuechengDaxueJisuanjiYuWangluoanquanJiangyiCis643644V01/img/settings-s.png
xuecheng_daxue_jisuanji_yu_wangluoanquan_jiangyi_cis643_644_v0_1-2024.3.2.0.dist-info/METADATA
xuecheng_daxue_jisuanji_yu_wangluoanquan_jiangyi_cis643_644_v0_1-2024.3.2.0.dist-info/WHEEL
xuecheng_daxue_jisuanji_yu_wangluoanquan_jiangyi_cis643_644_v0_1-2024.3.2.0.dist-info/entry_points.txt
xuecheng_daxue_jisuanji_yu_wangluoanquan_jiangyi_cis643_644_v0_1-2024.3.2.0.dist-info/top_level.txt
xuecheng_daxue_jisuanji_yu_wangluoanquan_jiangyi_cis643_644_v0_1-2024.3.2.0.dist-info/RECORD
